geomm/__init__.py
geomm/_print_version.py
geomm/_version.py
geomm/arrhenius.py
geomm/box_vectors.py
geomm/centering.py
geomm/centroid.py
geomm/distance.py
geomm/free_energy.py
geomm/grouping.py
geomm/kinetic_energy.py
geomm/pyqcprot.c
geomm/pyqcprot.cpython-312-darwin.so
geomm/pyqcprot.pyx
geomm/rmsd.py
geomm/sasa.py
geomm/superimpose.py
geomm/theobald_qcp.py
geomm/elements/__init__.py
geomm/elements/data.py
geomm-0.3.dist-info/licenses/AUTHORS.org
geomm-0.3.dist-info/licenses/LICENSE
geomm-0.3.dist-info/METADATA
geomm-0.3.dist-info/WHEEL
geomm-0.3.dist-info/top_level.txt
geomm-0.3.dist-info/RECORD
