Metadata-Version: 2.4
Name: geomm
Version: 0.3
Summary: A simple no-nonsense library for computing common geometry on macromolecular systems.
Home-page: https://github.com/ADicksonLab/geomm
Author: Samuel D. Lotz
Author-email: samuel.lotz@salotz.info
License: MIT
Keywords: geometry chemistry macromolecules protein structural-informatics
Classifier: Topic :: Utilities
Classifier: License :: OSI Approved :: MIT License
Classifier: Programming Language :: Python :: 3
License-File: LICENSE
License-File: AUTHORS.org
Requires-Dist: numpy
Requires-Dist: scipy
Requires-Dist: pint
Provides-Extra: all
Dynamic: author
Dynamic: author-email
Dynamic: classifier
Dynamic: home-page
Dynamic: keywords
Dynamic: license
Dynamic: license-file
Dynamic: provides-extra
Dynamic: requires-dist
Dynamic: summary
